ghwflint/__init__.py
ghwflint/__main__.py
ghwflint/definitions/gh_event_names.txt
ghwflint/definitions/gh_workflow_paths.txt
ghwflint/definitions/gh_workflow_paths_custom.txt
ghwflint/definitions.py
ghwflint/matchers.py
ghwflint/rules/__init__.py
ghwflint/rules/jobneeds.py
ghwflint/rules/unknownkeys.py
ghwflint/rules/validator.py
ghwflint/validator.py
ghwflint-1.0.1.dist-info/LICENSE
ghwflint-1.0.1.dist-info/WHEEL
ghwflint-1.0.1.dist-info/entry_points.txt
ghwflint-1.0.1.dist-info/METADATA
ghwflint-1.0.1.dist-info/RECORD
