Metadata-Version: 2.1
Name: ghwflint
Version: 1.0.1
Summary: 
Home-page: https://github.com/release-engineers/lint-github-workflow
Author: SkPhilipp
Author-email: philipp@release-engineers.com
Requires-Python: >=3.11,<4.0
Classifier: Programming Language :: Python :: 3
Classifier: Programming Language :: Python :: 3.11
Requires-Dist: ruamel.yaml (==0.17.21)
